slither/__init__.py
slither/cli.py
slither/tree.py
slither_cli-0.1.1.dist-info/METADATA
slither_cli-0.1.1.dist-info/WHEEL
slither_cli-0.1.1.dist-info/entry_points.txt
slither_cli-0.1.1.dist-info/RECORD
