Metadata-Version: 2.4
Name: slither-cli
Version: 0.1.1
Summary: Display directory structure as a tree in your terminal
Project-URL: Homepage, https://github.com/jesshart/slither-cli
Project-URL: Repository, https://github.com/jesshart/slither-cli
Project-URL: Issues, https://github.com/jesshart/slither-cli/issues
Author-email: Jesse Hart <jesse@jesshart.com>
License-Expression: MIT
Classifier: Development Status :: 3 - Alpha
Classifier: Environment :: Console
Classifier: Intended Audience :: Developers
Classifier: License :: OSI Approved :: MIT License
Classifier: Programming Language :: Python :: 3
Classifier: Programming Language :: Python :: 3.13
Classifier: Topic :: Software Development :: Libraries :: Python Modules
Classifier: Topic :: Utilities
Requires-Python: >=3.13
Requires-Dist: typer>=0.12.0
